cricket_cookie/__init__.py
cricket_cookie/env.py
cricket_cookie/login.py
cricket_cookie/rest_client.py
cricket_cookie/cli/__init__.py
cricket_cookie/cli/__main__.py
cricket_cookie/openapi/__init__.py
cricket_cookie/openapi/api_client.py
cricket_cookie/openapi/configuration.py
cricket_cookie/openapi/rest.py
cricket_cookie/openapi/api/__init__.py
cricket_cookie/openapi/api/auth_service_api.py
cricket_cookie/openapi/api/cluster_service_api.py
cricket_cookie/openapi/api/lightningapp_service_api.py
cricket_cookie/openapi/api/projects_service_api.py
cricket_cookie/openapi/api/user_service_api.py
cricket_cookie/openapi/models/__init__.py
cricket_cookie/openapi/models/body.py
cricket_cookie/openapi/models/body1.py
cricket_cookie/openapi/models/body2.py
cricket_cookie/openapi/models/body3.py
cricket_cookie/openapi/models/body4.py
cricket_cookie/openapi/models/body5.py
cricket_cookie/openapi/models/externalv1_cluster.py
cricket_cookie/openapi/models/externalv1_lightningapp.py
cricket_cookie/openapi/models/gridv1_image_spec.py
cricket_cookie/openapi/models/instance_type_availability.py
cricket_cookie/openapi/models/protobuf_any.py
cricket_cookie/openapi/models/rpc_status.py
cricket_cookie/openapi/models/v1_aws_cluster_driver_spec.py
cricket_cookie/openapi/models/v1_azure_cluster_driver_spec.py
cricket_cookie/openapi/models/v1_azure_cluster_driver_status.py
cricket_cookie/openapi/models/v1_cluster_driver.py
cricket_cookie/openapi/models/v1_cluster_driver_status.py
cricket_cookie/openapi/models/v1_cluster_performance_profile.py
cricket_cookie/openapi/models/v1_cluster_spec.py
cricket_cookie/openapi/models/v1_cluster_state.py
cricket_cookie/openapi/models/v1_cluster_status.py
cricket_cookie/openapi/models/v1_cluster_type.py
cricket_cookie/openapi/models/v1_compute_config.py
cricket_cookie/openapi/models/v1_container_resources.py
cricket_cookie/openapi/models/v1_create_cluster_request.py
cricket_cookie/openapi/models/v1_create_cluster_response.py
cricket_cookie-0.0.5.dist-info/METADATA
cricket_cookie-0.0.5.dist-info/WHEEL
cricket_cookie-0.0.5.dist-info/entry_points.txt
cricket_cookie-0.0.5.dist-info/top_level.txt
cricket_cookie-0.0.5.dist-info/RECORD
