Metadata-Version: 2.1
Name: cricket-cookie
Version: 0.0.5
Summary: Cricket Cookie
Home-page: https://cricket-cookies.com
Author: Grid.ai
Author-email: grid-eng@grid.ai
License: UNKNOWN
Platform: UNKNOWN
Classifier: Programming Language :: Python
Classifier: Programming Language :: Python :: 3.7
Classifier: Programming Language :: Python :: 3.8
Requires-Python: >=3.7.0
Requires-Dist: click
Requires-Dist: fastapi[all]
Requires-Dist: pyjwt
Requires-Dist: requests (==2.27.1)
Requires-Dist: rich (==11.2.0)
Requires-Dist: six (==1.16.0)
Requires-Dist: urllib3 (==1.26.8)
